{
	"@context": {
		"@language": "en",
		"dcat": "http://www.w3.org/ns/dcat#",
		"dct": "http://purl.org/dc/terms/",
		"ex": "http://www.example.org/def/historical-data#",
		"qb": "http://purl.org/linked-data/cube#" 
	} ,
	"title": "Camborne data",
	"description": "Historical observation weather data for Camborne",
	"license": "http://www.nationalarchives.gov.uk/doc/open-government-licence/version/2/",
	"spatial": "http://data.ordnancesurvey.co.uk/id/50kGazetteer/42095",
	"qb:structure": "ex:dsd1",
	"resources": [{
		"@id": "source/cambornedata.csv",
		"name": "cambornedata",
		"rowURL": "record-{year}-{month}",
		"tableSchema": {
			"columns": [{
				"name": "year",
				"title": "Year of observation"
			},{
				"name": "month",
				"title": "Month of observation"
			},{
				"name": "tmax",
				"title": "Mean daily maximum temperature",
				"required": true
			},{
				"name": "tmax-qualifier",
				"title": "Qualifier for value of mean daily maximum temperature"
			},{
				"name": "tmin",
				"title": "Mean daily minimum temperature",
				"required": true
			},{
				"name": "tmin-qualifier",
				"title": "Qualifier for value of mean daily minimum temperature"
			},{
				"name": "af",
				"title": "Number of days of air frost",
				"required": true
			},{
				"name": "af-qualifier",
				"title": "Qualifier for value of number of days of air frost"
			},{
				"name": "rain",
				"title": "Total rain accumulation",
				"required": true
			},{
				"name": "rain-qualifier",
				"title": "Qualifier for value of total rain accumulation"
			},{
				"name": "sun",
				"title": "Total sunshine duration",
				"required": true
			},{
				"name": "sun-qualifier",
				"title": "Qualifier for value of total sunshine duration"
			},{
				"name": "qc-status",
				"title": "Quality control status for observation record"
			}]
		},
	}]
}